syrtis/__init__.py
syrtis/configuration.py
syrtis/habitat.py
syrtis/material.py
syrtis/shell.py
syrtis/solver.py
syrtis/solvermanager.py
syrtis/tools.py
syrtis-0.1.0.dist-info/LICENSE
syrtis-0.1.0.dist-info/METADATA
syrtis-0.1.0.dist-info/WHEEL
syrtis-0.1.0.dist-info/top_level.txt
syrtis-0.1.0.dist-info/RECORD
